ocrd_anybaseocr/__init__.py
ocrd_anybaseocr/constants.py
ocrd_anybaseocr/ocrd-tool.json
ocrd_anybaseocr/params.json
ocrd_anybaseocr/tensorflow_importer.py
ocrd_anybaseocr/cli/__init__.py
ocrd_anybaseocr/cli/ocrd_anybaseocr_binarize.py
ocrd_anybaseocr/cli/ocrd_anybaseocr_block_segmentation.py
ocrd_anybaseocr/cli/ocrd_anybaseocr_cropping.py
ocrd_anybaseocr/cli/ocrd_anybaseocr_deskew.py
ocrd_anybaseocr/cli/ocrd_anybaseocr_dewarp.py
ocrd_anybaseocr/cli/ocrd_anybaseocr_layout_analysis.py
ocrd_anybaseocr/cli/ocrd_anybaseocr_textline.py
ocrd_anybaseocr/cli/ocrd_anybaseocr_tiseg.py
ocrd_anybaseocr/mrcnn/__init__.py
ocrd_anybaseocr/mrcnn/config.py
ocrd_anybaseocr/mrcnn/model.py
ocrd_anybaseocr/mrcnn/parallel_model.py
ocrd_anybaseocr/mrcnn/utils.py
ocrd_anybaseocr/pix2pixhd/__init__.py
ocrd_anybaseocr/pix2pixhd/encode_features.py
ocrd_anybaseocr/pix2pixhd/precompute_feature_maps.py
ocrd_anybaseocr/pix2pixhd/run_engine.py
ocrd_anybaseocr/pix2pixhd/test.py
ocrd_anybaseocr/pix2pixhd/train.py
ocrd_anybaseocr/pix2pixhd/data/__init__.py
ocrd_anybaseocr/pix2pixhd/data/aligned_dataset.py
ocrd_anybaseocr/pix2pixhd/data/base_data_loader.py
ocrd_anybaseocr/pix2pixhd/data/base_dataset.py
ocrd_anybaseocr/pix2pixhd/data/custom_dataset_data_loader.py
ocrd_anybaseocr/pix2pixhd/data/data_loader.py
ocrd_anybaseocr/pix2pixhd/data/image_folder.py
ocrd_anybaseocr/pix2pixhd/models/__init__.py
ocrd_anybaseocr/pix2pixhd/models/base_model.py
ocrd_anybaseocr/pix2pixhd/models/models.py
ocrd_anybaseocr/pix2pixhd/models/networks.py
ocrd_anybaseocr/pix2pixhd/models/pix2pixHD_model.py
ocrd_anybaseocr/pix2pixhd/models/ui_model.py
ocrd_anybaseocr/pix2pixhd/options/__init__.py
ocrd_anybaseocr/pix2pixhd/options/base_options.py
ocrd_anybaseocr/pix2pixhd/options/test_options.py
ocrd_anybaseocr/pix2pixhd/options/train_options.py
ocrd_anybaseocr/pix2pixhd/util/__init__.py
ocrd_anybaseocr/pix2pixhd/util/html.py
ocrd_anybaseocr/pix2pixhd/util/image_pool.py
ocrd_anybaseocr/pix2pixhd/util/util.py
ocrd_anybaseocr-1.8.2.dist-info/LICENSE
ocrd_anybaseocr-1.8.2.dist-info/METADATA
ocrd_anybaseocr-1.8.2.dist-info/WHEEL
ocrd_anybaseocr-1.8.2.dist-info/entry_points.txt
ocrd_anybaseocr-1.8.2.dist-info/top_level.txt
ocrd_anybaseocr-1.8.2.dist-info/RECORD
