Metadata-Version: 2.1
Name: ocrd-anybaseocr
Version: 1.8.2
Summary: UNKNOWN
Home-page: https://github.com/OCR-D/ocrd_anybaseocr
Author: DFKI
Author-email: Saqib.Bukhari@dfki.de, Mohammad_mohsin.reza@dfki.de
License: Apache License 2.0
Platform: UNKNOWN
License-File: LICENSE
Requires-Dist: keras
Requires-Dist: keras-preprocessing
Requires-Dist: numpy (>=1.15.4)
Requires-Dist: ocrd (>=2.31)
Requires-Dist: ocrd-fork-pylsd (>=0.0.4)
Requires-Dist: ocrd-fork-ocropy (>=1.4.0a4)
Requires-Dist: opencv-python-headless (>=3.4)
Requires-Dist: pandas
Requires-Dist: scikit-image (>=0.17.2)
Requires-Dist: scipy (>=1.4.1)
Requires-Dist: setuptools (>=41.0.0)
Requires-Dist: shapely
Requires-Dist: tensorflow
Requires-Dist: torch (>=1.1.0)
Requires-Dist: torchvision (>=0.6.1)
Requires-Dist: pix2pixhd
